MorePie/ErrorSuppressor.py
MorePie/MoreConsole.py
MorePie/Sums.py
MorePie/__init__.py
MorePie/MoreTypes/HashMaps.py
MorePie/MoreTypes/Matrixes.py
MorePie/MoreTypes/__init__.py
MorePie/MoreTypes/HelperFiles/MorePyOverloading.py
MorePie/MoreTypes/HelperFiles/__init__.py
MorePie-1.0.1.dist-info/METADATA
MorePie-1.0.1.dist-info/WHEEL
MorePie-1.0.1.dist-info/license.txt
MorePie-1.0.1.dist-info/top_level.txt
MorePie-1.0.1.dist-info/RECORD
