Metadata-Version: 2.1
Name: MorePie
Version: 1.0.1
Summary: Does Python not have enough tools? MorePie is here to help!
Home-page: https://github.com/cornusandu/MorePy
Author: Sandu Bogdan
Author-email: bogdanelsandu@hotmail.com
Project-URL: Bug Tracker, https://github.com/cornusandu/MorePy/issues
Project-URL: GitHub Repository, https://github.com/cornusandu/MorePy
Classifier: Programming Language :: Python :: 3
Classifier: License :: OSI Approved :: MIT License
Classifier: Operating System :: OS Independent
Requires-Python: >=3.10
License-File: license.txt
